allan_tool/__init__.py
allan_tool/tool.py
allan_tool-4.0.0.dist-info/LICENSE
allan_tool-4.0.0.dist-info/METADATA
allan_tool-4.0.0.dist-info/WHEEL
allan_tool-4.0.0.dist-info/top_level.txt
allan_tool-4.0.0.dist-info/RECORD
