Metadata-Version: 2.1
Name: allan-tool
Version: 4.0.0
Summary: p function and t function
Home-page: https://github.com/iwanglei1
Author: Allan Wang
Author-email: lawther@mails.cust.edu.cn
Classifier: Programming Language :: Python :: 3
Classifier: License :: OSI Approved :: MIT License
Classifier: Operating System :: OS Independent
License-File: LICENSE
